    {
        "id": "2",
        "name": "McDonald's",
        "image": "https://example.com/mcdonalds-image.jpg",
        "address": "155 Bloor Street",
        "description": "McDonald's offers a wide range of fast food options, from classic burgers to breakfast items. Known for its convenience and quick meals.",
        "comments": [
            {
                "writer": "Emily Johnson",
                "timestamp": "2023-11-18T09:45:00Z",
                "text": "Their breakfast menu is fantastic."
            },
            {
                "writer": "Mike Brown",
                "timestamp": "2023-11-17T15:20:00Z",
                "text": "The service can be slow during peak hours."
            }
        ]
    }